matsense/__init__.py
matsense/blank_template.yaml
matsense/client.py
matsense/cmd.py
matsense/data.py
matsense/datasetter.py
matsense/exception.py
matsense/filemanager.py
matsense/server.py
matsense/tools.py
matsense/uclient.py
matsense/process/__init__.py
matsense/process/blob_parser.py
matsense/process/data_handler.py
matsense/process/interpolator.py
matsense/process/point_tool.py
matsense/process/pressure_selector.py
matsense/process/processor.py
matsense/serverkit/__init__.py
matsense/serverkit/flag.py
matsense/serverkit/proc.py
matsense/serverkit/userver.py
matsense/visual/__init__.py
matsense/visual/player.py
matsense/visual/player1d.py
matsense/visual/player_matplot.py
matsense/visual/player_pyqtgraph.py
matsense/visual/util.py
MatSense-0.4.1.dist-info/METADATA
MatSense-0.4.1.dist-info/WHEEL
MatSense-0.4.1.dist-info/entry_points.txt
MatSense-0.4.1.dist-info/top_level.txt
MatSense-0.4.1.dist-info/RECORD
