Metadata-Version: 2.1
Name: MatSense
Version: 0.4.1
Summary: A toolkit for matrix sensor data processing 阵列传感器数据处理工具库
Home-page: https://github.com/atomiechen/MatSense
Author: Atomie CHEN
Author-email: atomic_cwh@163.com
Project-URL: Bug Tracker, https://github.com/atomiechen/MatSense/issues
Project-URL: Source Code, https://github.com/atomiechen/MatSense
Keywords: matrix sensor,signal processing,3D visualization
Classifier: Development Status :: 4 - Beta
Classifier: Programming Language :: Python :: 3
Classifier: Operating System :: OS Independent
Requires-Python: >=3.6, <4
Requires-Dist: numpy >=1.19.2
Requires-Dist: scipy >=1.5.4
Requires-Dist: pyserial >=3.5
Requires-Dist: PyYAML >=5.4.1
Requires-Dist: pyparsing >=2.4.7
Requires-Dist: matplotlib <=3.4,>=3.3
Provides-Extra: pyqtgraph
Requires-Dist: pyqtgraph ==0.11.* ; extra == 'pyqtgraph'
Requires-Dist: PyOpenGL ~=3.1.5 ; extra == 'pyqtgraph'
Requires-Dist: PyQt5 ==5.12.* ; (python_version == "3.7") and extra == 'pyqtgraph'
Requires-Dist: PyQt5 ==5.15.* ; (python_version == "3.8") and extra == 'pyqtgraph'
Requires-Dist: PyQt6 ==6.0.* ; (python_version == "3.9") and extra == 'pyqtgraph'
